vectorplot/__init__.py
vectorplot/vp.py
vectorplot-0.0.28.dist-info/METADATA
vectorplot-0.0.28.dist-info/WHEEL
vectorplot-0.0.28.dist-info/top_level.txt
vectorplot-0.0.28.dist-info/RECORD
