Metadata-Version: 2.1
Name: vectorplot
Version: 0.0.28
Summary: Pacote python para plotagem de vetores em planos bidimensionais e espaços tridimensionais
Home-page: https://github.com/marcos-de-sousa/vectorplot
Author: Marcos Paulo Alves de Sousa
Author-email: desousa.mpa@gmail.com
License: MIT License
Keywords: Pacote
Requires-Dist: numpy
Requires-Dist: matplotlib
